{"GlobalPropertiesHash":"2ilJ2M8+ZdH0swl4cXFj9Ji8kay0R08ISE/fEc+OL0o=","FingerprintPatternsHash":"8ZRc1sGeVrPBx4lD717BgRaQekyh78QKV9SKsdt638U=","PropertyOverridesHash":"8ZRc1sGeVrPBx4lD717BgRaQekyh78QKV9SKsdt638U=","InputHashes":["V9SN4XTNYdm7TQ2T8SRcjKxV6UOq5Ov9g2ivsoXy120=","t\u002BJTJoijsx5XhTeG62GuRUWD6QTdgNtZBZuSF/\u002BGr4c=","POB\u002BKAa98\u002B6QOvCR1OuXDKE9VgOq5sX0ESWS6s\u002BS6X0=","hKvcU1E95xN5e9GY1Bk0j3TgpApBuKU4oMAWXHr77fk=","WYJaoaqMneHdRMX6Ug0xqXx43UQuVUMuuA\u002B50yrO5\u002Bw=","bTlL2Wfp/Px/YbNFyMh61NX21sObYuV2qFRALqTk8BI=","j/5hM\u002B2nh9DGQ7J8EAWdel8dZTcR0B851R\u002BQqAu/nRA=","hL1pu\u002BgrMy1C0TSlyh1jFbpwZ\u002BagD59\u002BB\u002BMD9r2ICoU=","kcF69sNoQttaDZ/ZwELIQcdjPVRwCl96MW8S/TJu3Oc=","4aUt8q3vorajPvaXXm4Qlzgx2FRy9ZUMvTZGSsk8A7A=","lhPuXJqqv4iIGEbWxbrfOX/OaM8zSdcL4QMm\u002BTYe05A=","OE7kTGRiYAmHgMU6iUVRet7QEaczYSpJ7l4CLVvPEN0=","htmqMKAx5E5MDqMASheGZEegoICn4byLfcP6MvZHVvE=","rxpg2FRgXEH8p80bYU8HJOM3koNwITkmJfnCGU8P\u002BFo=","TeG9CoGrMj5nxer6yzHNF8zJHU5KsxJ3WkWaDOmso0k=","L7eFClbOW5rabeVwI8ljhe2AQR679AinolCQx\u002BsGba4=","NGYnhibmefS/yPQnDZMgkUKeJVttu4eAhdkeHJeaU/8=","ck5VqH88wjOuPMIUdb7SCeqOWSMjNPAn2ibXHbthqkk=","TjfTgi07Xc\u002BW2UcDcvWVJSetMk6MtP8lOnP4FZnmN6o=","l8qvB0eAjawmyYWSMAZXZy1EPrAKuw7SJG6w8st6nRo=","Xso3BC3HnW9OR5E4cDfKQJFvyMKwW7WINsDSzxq0pDU=","q\u002BMnEhdfbMl7fpvWk8D4QOnzGD\u002B8HNcm6rTDeRPHNQc=","OI2ww56DsHf5pRQ5oFnPNw145n7X63QSGI4cmxQEs2M=","OBHGhoT4a2DyZI9sYHCkTY1hUJCfM9qSPOqIXHLQfDs=","ia4YqHr9zmTVULMutH1QwBlF6NoUOqdyLUUam1KERbE=","BcqYKYAIEh8LALdvigulNdeB23S0vcd7i/zJUP4iGxk=","tivk942RSZzx\u002BLndo5xVWKhIW2dQn\u002BJULnWCIkP7qs8=","LeKK7lFI\u002BQHJYaNneRcorUxZrJuNcfrA4tvfx8s5u\u002BM=","LVgInINb3gTngzQYR9a9O6adKnS8JlNBhKqelysjrkI=","tep8xeq/7WUJ1b5pVdGK8plfgBq5Y8BDT4WS7RniGX8=","VVDHv/k8Nl1GTbazhUyhhgSVd1bfn/hXPuKjzxZ/Oiw=","76lr/Mli5TtUXy6Khm5YdkaOv0LbYezBTZGxNUgXjEw=","reqdiaijtU9ZJmQCNU//N8a5VHmlv\u002BOZYrGBDJDsVYU=","AUWlclhK1xmkpNVECnj/n2v0kZBjSXGMG0jrofpw8yI=","YD0TK400t81NxySSnydZUinijTSdSIpFMBliDKWMfdk="],"CachedAssets":{"V9SN4XTNYdm7TQ2T8SRcjKxV6UOq5Ov9g2ivsoXy120=":{"Identity":"Z:\\EVALUATION\\PROJET\\ebillets_jo2024\\ebillets_jo2024\\obj\\Debug\\net9.0\\compressed\\up7elrow0y-hdhjllpya4.gz","SourceId":"ebillets_jo2024","SourceType":"Discovered","ContentRoot":"Z:\\EVALUATION\\PROJET\\ebillets_jo2024\\ebillets_jo2024\\obj\\Debug\\net9.0\\compressed\\","BasePath":"_content/ebillets_jo2024","RelativePath":"css/site#[.{fingerprint=hdhjllpya4}]?.css.gz","AssetKind":"All","AssetMode":"All","AssetRole":"Alternative","AssetMergeBehavior":null,"AssetMergeSource":"","RelatedAsset":"Z:\\EVALUATION\\PROJET\\ebillets_jo2024\\ebillets_jo2024\\wwwroot\\css\\site.css","AssetTraitName":"Content-Encoding","AssetTraitValue":"gzip","Fingerprint":"0tevtyurkr","Integrity":"TP7j5uZuJdntcOfcko7umOSdXFMdhRUKfjFd0AWnaFI=","CopyToOutputDirectory":"Never","CopyToPublishDirectory":"PreserveNewest","OriginalItemSpec":"Z:\\EVALUATION\\PROJET\\ebillets_jo2024\\ebillets_jo2024\\wwwroot\\css\\site.css","FileLength":641,"LastWriteTime":"2025-10-12T09:03:03.9585019+00:00"},"t\u002BJTJoijsx5XhTeG62GuRUWD6QTdgNtZBZuSF/\u002BGr4c=":{"Identity":"Z:\\EVALUATION\\PROJET\\ebillets_jo2024\\ebillets_jo2024\\obj\\Debug\\net9.0\\compressed\\3qrz04kjgw-90yqlj465b.gz","SourceId":"ebillets_jo2024","SourceType":"Discovered","ContentRoot":"Z:\\EVALUATION\\PROJET\\ebillets_jo2024\\ebillets_jo2024\\obj\\Debug\\net9.0\\compressed\\","BasePath":"_content/ebillets_jo2024","RelativePath":"favicon#[.{fingerprint=90yqlj465b}]?.ico.gz","AssetKind":"All","AssetMode":"All","AssetRole":"Alternative","AssetMergeBehavior":null,"AssetMergeSource":"","RelatedAsset":"Z:\\EVALUATION\\PROJET\\ebillets_jo2024\\ebillets_jo2024\\wwwroot\\favicon.ico","AssetTraitName":"Content-Encoding","AssetTraitValue":"gzip","Fingerprint":"xngppdbdhq","Integrity":"nR0lNhVJOqtsVYCBNYXOoTLPTwP88AJKUlf4evu9xkE=","CopyToOutputDirectory":"Never","CopyToPublishDirectory":"PreserveNewest","OriginalItemSpec":"Z:\\EVALUATION\\PROJET\\ebillets_jo2024\\ebillets_jo2024\\wwwroot\\favicon.ico","FileLength":9431,"LastWriteTime":"2025-10-12T09:03:03.9625001+00:00"},"POB\u002BKAa98\u002B6QOvCR1OuXDKE9VgOq5sX0ESWS6s\u002BS6X0=":{"Identity":"Z:\\EVALUATION\\PROJET\\ebillets_jo2024\\ebillets_jo2024\\obj\\Debug\\net9.0\\compressed\\4pdbx7miy3-0n9f8i66x6.gz","SourceId":"ebillets_jo2024","SourceType":"Discovered","ContentRoot":"Z:\\EVALUATION\\PROJET\\ebillets_jo2024\\ebillets_jo2024\\obj\\Debug\\net9.0\\compressed\\","BasePath":"_content/ebillets_jo2024","RelativePath":"js/site#[.{fingerprint=0n9f8i66x6}]?.js.gz","AssetKind":"All","AssetMode":"All","AssetRole":"Alternative","AssetMergeBehavior":null,"AssetMergeSource":"","RelatedAsset":"Z:\\EVALUATION\\PROJET\\ebillets_jo2024\\ebillets_jo2024\\wwwroot\\js\\site.js","AssetTraitName":"Content-Encoding","AssetTraitValue":"gzip","Fingerprint":"kimwdh415r","Integrity":"/Mp0M0f41yhPFkzdAUe9swvvjRlvmhMty1mZZSRdmG0=","CopyToOutputDirectory":"Never","CopyToPublishDirectory":"PreserveNewest","OriginalItemSpec":"Z:\\EVALUATION\\PROJET\\ebillets_jo2024\\ebillets_jo2024\\wwwroot\\js\\site.js","FileLength":186,"LastWriteTime":"2025-10-12T09:03:03.9639075+00:00"},"hKvcU1E95xN5e9GY1Bk0j3TgpApBuKU4oMAWXHr77fk=":{"Identity":"Z:\\EVALUATION\\PROJET\\ebillets_jo2024\\ebillets_jo2024\\obj\\Debug\\net9.0\\compressed\\2aq6il8xc7-9n0ta5ieki.gz","SourceId":"ebillets_jo2024","SourceType":"Discovered","ContentRoot":"Z:\\EVALUATION\\PROJET\\ebillets_jo2024\\ebillets_jo2024\\obj\\Debug\\net9.0\\compressed\\","BasePath":"_content/ebillets_jo2024","RelativePath":"lib/bootstrap/dist/css/bootstrap-grid#[.{fingerprint=9n0ta5ieki}]?.css.gz","AssetKind":"All","AssetMode":"All","AssetRole":"Alternative","AssetMergeBehavior":null,"AssetMergeSource":"","RelatedAsset":"Z:\\EVALUATION\\PROJET\\ebillets_jo2024\\ebillets_jo2024\\wwwroot\\lib\\bootstrap\\dist\\css\\bootstrap-grid.css","AssetTraitName":"Content-Encoding","AssetTraitValue":"gzip","Fingerprint":"xhmut9o5n8","Integrity":"ZY60kbNkADk4KDRhW\u002BLL\u002BizegJBs9qdfvXorvDd7lIc=","CopyToOutputDirectory":"Never","CopyToPublishDirectory":"PreserveNewest","OriginalItemSpec":"Z:\\EVALUATION\\PROJET\\ebillets_jo2024\\ebillets_jo2024\\wwwroot\\lib\\bootstrap\\dist\\css\\bootstrap-grid.css","FileLength":6966,"LastWriteTime":"2025-10-12T09:03:03.965135+00:00"},"WYJaoaqMneHdRMX6Ug0xqXx43UQuVUMuuA\u002B50yrO5\u002Bw=":{"Identity":"Z:\\EVALUATION\\PROJET\\ebillets_jo2024\\ebillets_jo2024\\obj\\Debug\\net9.0\\compressed\\n5x38c0hhj-0i1dcxd824.gz","SourceId":"ebillets_jo2024","SourceType":"Discovered","ContentRoot":"Z:\\EVALUATION\\PROJET\\ebillets_jo2024\\ebillets_jo2024\\obj\\Debug\\net9.0\\compressed\\","BasePath":"_content/ebillets_jo2024","RelativePath":"lib/bootstrap/dist/css/bootstrap-grid.css#[.{fingerprint=0i1dcxd824}]?.map.gz","AssetKind":"All","AssetMode":"All","AssetRole":"Alternative","AssetMergeBehavior":null,"AssetMergeSource":"","RelatedAsset":"Z:\\EVALUATION\\PROJET\\ebillets_jo2024\\ebillets_jo2024\\wwwroot\\lib\\bootstrap\\dist\\css\\bootstrap-grid.css.map","AssetTraitName":"Content-Encoding","AssetTraitValue":"gzip","Fingerprint":"ligbo5mwl1","Integrity":"oytvk6SQ3cnlPxAF33gxI7GS06Rj2MrRoUPoiaFchjQ=","CopyToOutputDirectory":"Never","CopyToPublishDirectory":"PreserveNewest","OriginalItemSpec":"Z:\\EVALUATION\\PROJET\\ebillets_jo2024\\ebillets_jo2024\\wwwroot\\lib\\bootstrap\\dist\\css\\bootstrap-grid.css.map","FileLength":27062,"LastWriteTime":"2025-10-12T09:03:03.9625001+00:00"},"bTlL2Wfp/Px/YbNFyMh61NX21sObYuV2qFRALqTk8BI=":{"Identity":"Z:\\EVALUATION\\PROJET\\ebillets_jo2024\\ebillets_jo2024\\obj\\Debug\\net9.0\\compressed\\yajpiw3r28-vxs71z90fw.gz","SourceId":"ebillets_jo2024","SourceType":"Discovered","ContentRoot":"Z:\\EVALUATION\\PROJET\\ebillets_jo2024\\ebillets_jo2024\\obj\\Debug\\net9.0\\compressed\\","BasePath":"_content/ebillets_jo2024","RelativePath":"lib/bootstrap/dist/css/bootstrap-grid.min#[.{fingerprint=vxs71z90fw}]?.css.gz","AssetKind":"All","AssetMode":"All","AssetRole":"Alternative","AssetMergeBehavior":null,"AssetMergeSource":"","RelatedAsset":"Z:\\EVALUATION\\PROJET\\ebillets_jo2024\\ebillets_jo2024\\wwwroot\\lib\\bootstrap\\dist\\css\\bootstrap-grid.min.css","AssetTraitName":"Content-Encoding","AssetTraitValue":"gzip","Fingerprint":"otvwzz8k95","Integrity":"HFjfcB/gV8FeYhFO87HnfGGK/Ebdg885i044QcdVncY=","CopyToOutputDirectory":"Never","CopyToPublishDirectory":"PreserveNewest","OriginalItemSpec":"Z:\\EVALUATION\\PROJET\\ebillets_jo2024\\ebillets_jo2024\\wwwroot\\lib\\bootstrap\\dist\\css\\bootstrap-grid.min.css","FileLength":6029,"LastWriteTime":"2025-10-12T09:03:03.9675234+00:00"},"j/5hM\u002B2nh9DGQ7J8EAWdel8dZTcR0B851R\u002BQqAu/nRA=":{"Identity":"Z:\\EVALUATION\\PROJET\\ebillets_jo2024\\ebillets_jo2024\\obj\\Debug\\net9.0\\compressed\\yuym3zwpe8-jzb7jyrjvs.gz","SourceId":"ebillets_jo2024","SourceType":"Discovered","ContentRoot":"Z:\\EVALUATION\\PROJET\\ebillets_jo2024\\ebillets_jo2024\\obj\\Debug\\net9.0\\compressed\\","BasePath":"_content/ebillets_jo2024","RelativePath":"lib/bootstrap/dist/css/bootstrap-grid.min.css#[.{fingerprint=jzb7jyrjvs}]?.map.gz","AssetKind":"All","AssetMode":"All","AssetRole":"Alternative","AssetMergeBehavior":null,"AssetMergeSource":"","RelatedAsset":"Z:\\EVALUATION\\PROJET\\ebillets_jo2024\\ebillets_jo2024\\wwwroot\\lib\\bootstrap\\dist\\css\\bootstrap-grid.min.css.map","AssetTraitName":"Content-Encoding","AssetTraitValue":"gzip","Fingerprint":"iez2ehrrlx","Integrity":"ukFugDNptsdF2I0tTFVp\u002Bzrq3vCFvErB7PNxY2Pmf7s=","CopyToOutputDirectory":"Never","CopyToPublishDirectory":"PreserveNewest","OriginalItemSpec":"Z:\\EVALUATION\\PROJET\\ebillets_jo2024\\ebillets_jo2024\\wwwroot\\lib\\bootstrap\\dist\\css\\bootstrap-grid.min.css.map","FileLength":13935,"LastWriteTime":"2025-10-12T09:03:03.9738891+00:00"},"hL1pu\u002BgrMy1C0TSlyh1jFbpwZ\u002BagD59\u002BB\u002BMD9r2ICoU=":{"Identity":"Z:\\EVALUATION\\PROJET\\ebillets_jo2024\\ebillets_jo2024\\obj\\Debug\\net9.0\\compressed\\5w38owu3jh-nynt4yc5xr.gz","SourceId":"ebillets_jo2024","SourceType":"Discovered","ContentRoot":"Z:\\EVALUATION\\PROJET\\ebillets_jo2024\\ebillets_jo2024\\obj\\Debug\\net9.0\\compressed\\","BasePath":"_content/ebillets_jo2024","RelativePath":"lib/bootstrap/dist/css/bootstrap-reboot#[.{fingerprint=nynt4yc5xr}]?.css.gz","AssetKind":"All","AssetMode":"All","AssetRole":"Alternative","AssetMergeBehavior":null,"AssetMergeSource":"","RelatedAsset":"Z:\\EVALUATION\\PROJET\\ebillets_jo2024\\ebillets_jo2024\\wwwroot\\lib\\bootstrap\\dist\\css\\bootstrap-reboot.css","AssetTraitName":"Content-Encoding","AssetTraitValue":"gzip","Fingerprint":"yr6g57tbrs","Integrity":"ski9h0PufafI6hMaaPSRPSY\u002BiMBc1VbPoK1FYjUXHMQ=","CopyToOutputDirectory":"Never","CopyToPublishDirectory":"PreserveNewest","OriginalItemSpec":"Z:\\EVALUATION\\PROJET\\ebillets_jo2024\\ebillets_jo2024\\wwwroot\\lib\\bootstrap\\dist\\css\\bootstrap-reboot.css","FileLength":1737,"LastWriteTime":"2025-10-12T09:03:03.9685223+00:00"},"kcF69sNoQttaDZ/ZwELIQcdjPVRwCl96MW8S/TJu3Oc=":{"Identity":"Z:\\EVALUATION\\PROJET\\ebillets_jo2024\\ebillets_jo2024\\obj\\Debug\\net9.0\\compressed\\qixxhab4cs-tgg2bl5mrw.gz","SourceId":"ebillets_jo2024","SourceType":"Discovered","ContentRoot":"Z:\\EVALUATION\\PROJET\\ebillets_jo2024\\ebillets_jo2024\\obj\\Debug\\net9.0\\compressed\\","BasePath":"_content/ebillets_jo2024","RelativePath":"lib/bootstrap/dist/css/bootstrap-reboot.css#[.{fingerprint=tgg2bl5mrw}]?.map.gz","AssetKind":"All","AssetMode":"All","AssetRole":"Alternative","AssetMergeBehavior":null,"AssetMergeSource":"","RelatedAsset":"Z:\\EVALUATION\\PROJET\\ebillets_jo2024\\ebillets_jo2024\\wwwroot\\lib\\bootstrap\\dist\\css\\bootstrap-reboot.css.map","AssetTraitName":"Content-Encoding","AssetTraitValue":"gzip","Fingerprint":"2shzy9x2jj","Integrity":"PgWj9lwXprPCKRJlELXHPizyFeevIvOzAMOrcCGtBdI=","CopyToOutputDirectory":"Never","CopyToPublishDirectory":"PreserveNewest","OriginalItemSpec":"Z:\\EVALUATION\\PROJET\\ebillets_jo2024\\ebillets_jo2024\\wwwroot\\lib\\bootstrap\\dist\\css\\bootstrap-reboot.css.map","FileLength":17007,"LastWriteTime":"2025-10-12T09:03:03.9605007+00:00"},"4aUt8q3vorajPvaXXm4Qlzgx2FRy9ZUMvTZGSsk8A7A=":{"Identity":"Z:\\EVALUATION\\PROJET\\ebillets_jo2024\\ebillets_jo2024\\obj\\Debug\\net9.0\\compressed\\9y567692tj-brwg1hntyu.gz","SourceId":"ebillets_jo2024","SourceType":"Discovered","ContentRoot":"Z:\\EVALUATION\\PROJET\\ebillets_jo2024\\ebillets_jo2024\\obj\\Debug\\net9.0\\compressed\\","BasePath":"_content/ebillets_jo2024","RelativePath":"lib/bootstrap/dist/css/bootstrap-reboot.min#[.{fingerprint=brwg1hntyu}]?.css.gz","AssetKind":"All","AssetMode":"All","AssetRole":"Alternative","AssetMergeBehavior":null,"AssetMergeSource":"","RelatedAsset":"Z:\\EVALUATION\\PROJET\\ebillets_jo2024\\ebillets_jo2024\\wwwroot\\lib\\bootstrap\\dist\\css\\bootstrap-reboot.min.css","AssetTraitName":"Content-Encoding","AssetTraitValue":"gzip","Fingerprint":"450chlim9d","Integrity":"SK/uC88mzOjgHwihIpIpaGtZcvPkQkQKkO0iusPs\u002BZ0=","CopyToOutputDirectory":"Never","CopyToPublishDirectory":"PreserveNewest","OriginalItemSpec":"Z:\\EVALUATION\\PROJET\\ebillets_jo2024\\ebillets_jo2024\\wwwroot\\lib\\bootstrap\\dist\\css\\bootstrap-reboot.min.css","FileLength":1615,"LastWriteTime":"2025-10-12T09:03:03.9625001+00:00"},"lhPuXJqqv4iIGEbWxbrfOX/OaM8zSdcL4QMm\u002BTYe05A=":{"Identity":"Z:\\EVALUATION\\PROJET\\ebillets_jo2024\\ebillets_jo2024\\obj\\Debug\\net9.0\\compressed\\tbte4b80xq-gf2dxac9qe.gz","SourceId":"ebillets_jo2024","SourceType":"Discovered","ContentRoot":"Z:\\EVALUATION\\PROJET\\ebillets_jo2024\\ebillets_jo2024\\obj\\Debug\\net9.0\\compressed\\","BasePath":"_content/ebillets_jo2024","RelativePath":"lib/bootstrap/dist/css/bootstrap-reboot.min.css#[.{fingerprint=gf2dxac9qe}]?.map.gz","AssetKind":"All","AssetMode":"All","AssetRole":"Alternative","AssetMergeBehavior":null,"AssetMergeSource":"","RelatedAsset":"Z:\\EVALUATION\\PROJET\\ebillets_jo2024\\ebillets_jo2024\\wwwroot\\lib\\bootstrap\\dist\\css\\bootstrap-reboot.min.css.map","AssetTraitName":"Content-Encoding","AssetTraitValue":"gzip","Fingerprint":"m8laq02kqt","Integrity":"\u002Bvu0DGLWqkGPTrKaf7U22OpO4XImAF0LW8HvFHEnCKA=","CopyToOutputDirectory":"Never","CopyToPublishDirectory":"PreserveNewest","OriginalItemSpec":"Z:\\EVALUATION\\PROJET\\ebillets_jo2024\\ebillets_jo2024\\wwwroot\\lib\\bootstrap\\dist\\css\\bootstrap-reboot.min.css.map","FileLength":8039,"LastWriteTime":"2025-10-12T09:03:03.965135+00:00"},"OE7kTGRiYAmHgMU6iUVRet7QEaczYSpJ7l4CLVvPEN0=":{"Identity":"Z:\\EVALUATION\\PROJET\\ebillets_jo2024\\ebillets_jo2024\\obj\\Debug\\net9.0\\compressed\\68tixml9mp-gawgt6fljy.gz","SourceId":"ebillets_jo2024","SourceType":"Discovered","ContentRoot":"Z:\\EVALUATION\\PROJET\\ebillets_jo2024\\ebillets_jo2024\\obj\\Debug\\net9.0\\compressed\\","BasePath":"_content/ebillets_jo2024","RelativePath":"lib/bootstrap/dist/css/bootstrap#[.{fingerprint=gawgt6fljy}]?.css.gz","AssetKind":"All","AssetMode":"All","AssetRole":"Alternative","AssetMergeBehavior":null,"AssetMergeSource":"","RelatedAsset":"Z:\\EVALUATION\\PROJET\\ebillets_jo2024\\ebillets_jo2024\\wwwroot\\lib\\bootstrap\\dist\\css\\bootstrap.css","AssetTraitName":"Content-Encoding","AssetTraitValue":"gzip","Fingerprint":"20hnowj6dn","Integrity":"LgKX0350Ug6XsDByPQMOQx1sihJrlzqNLL47LiyoSQ4=","CopyToOutputDirectory":"Never","CopyToPublishDirectory":"PreserveNewest","OriginalItemSpec":"Z:\\EVALUATION\\PROJET\\ebillets_jo2024\\ebillets_jo2024\\wwwroot\\lib\\bootstrap\\dist\\css\\bootstrap.css","FileLength":25746,"LastWriteTime":"2025-10-12T09:03:03.9708874+00:00"},"htmqMKAx5E5MDqMASheGZEegoICn4byLfcP6MvZHVvE=":{"Identity":"Z:\\EVALUATION\\PROJET\\ebillets_jo2024\\ebillets_jo2024\\obj\\Debug\\net9.0\\compressed\\4a4idt580j-k9n1kkbua6.gz","SourceId":"ebillets_jo2024","SourceType":"Discovered","ContentRoot":"Z:\\EVALUATION\\PROJET\\ebillets_jo2024\\ebillets_jo2024\\obj\\Debug\\net9.0\\compressed\\","BasePath":"_content/ebillets_jo2024","RelativePath":"lib/bootstrap/dist/css/bootstrap.css#[.{fingerprint=k9n1kkbua6}]?.map.gz","AssetKind":"All","AssetMode":"All","AssetRole":"Alternative","AssetMergeBehavior":null,"AssetMergeSource":"","RelatedAsset":"Z:\\EVALUATION\\PROJET\\ebillets_jo2024\\ebillets_jo2024\\wwwroot\\lib\\bootstrap\\dist\\css\\bootstrap.css.map","AssetTraitName":"Content-Encoding","AssetTraitValue":"gzip","Fingerprint":"8nia3m3p3a","Integrity":"HBgFcfSZJMq1nxRljAc5eNlMAVuXqU0lQoR9rBIy968=","CopyToOutputDirectory":"Never","CopyToPublishDirectory":"PreserveNewest","OriginalItemSpec":"Z:\\EVALUATION\\PROJET\\ebillets_jo2024\\ebillets_jo2024\\wwwroot\\lib\\bootstrap\\dist\\css\\bootstrap.css.map","FileLength":98033,"LastWriteTime":"2025-10-12T09:03:03.9758892+00:00"},"rxpg2FRgXEH8p80bYU8HJOM3koNwITkmJfnCGU8P\u002BFo=":{"Identity":"Z:\\EVALUATION\\PROJET\\ebillets_jo2024\\ebillets_jo2024\\obj\\Debug\\net9.0\\compressed\\8ohasfwld3-etnb7xlipe.gz","SourceId":"ebillets_jo2024","SourceType":"Discovered","ContentRoot":"Z:\\EVALUATION\\PROJET\\ebillets_jo2024\\ebillets_jo2024\\obj\\Debug\\net9.0\\compressed\\","BasePath":"_content/ebillets_jo2024","RelativePath":"lib/bootstrap/dist/css/bootstrap.min#[.{fingerprint=etnb7xlipe}]?.css.gz","AssetKind":"All","AssetMode":"All","AssetRole":"Alternative","AssetMergeBehavior":null,"AssetMergeSource":"","RelatedAsset":"Z:\\EVALUATION\\PROJET\\ebillets_jo2024\\ebillets_jo2024\\wwwroot\\lib\\bootstrap\\dist\\css\\bootstrap.min.css","AssetTraitName":"Content-Encoding","AssetTraitValue":"gzip","Fingerprint":"fg8y3a0rbt","Integrity":"T2rPGX2rORFBp2vX1wlC4q43KPqCjKbVkY\u002BVHIDgmP0=","CopyToOutputDirectory":"Never","CopyToPublishDirectory":"PreserveNewest","OriginalItemSpec":"Z:\\EVALUATION\\PROJET\\ebillets_jo2024\\ebillets_jo2024\\wwwroot\\lib\\bootstrap\\dist\\css\\bootstrap.min.css","FileLength":23242,"LastWriteTime":"2025-10-12T09:03:03.9708874+00:00"},"TeG9CoGrMj5nxer6yzHNF8zJHU5KsxJ3WkWaDOmso0k=":{"Identity":"Z:\\EVALUATION\\PROJET\\ebillets_jo2024\\ebillets_jo2024\\obj\\Debug\\net9.0\\compressed\\0rhvt52mtj-kao5znno1s.gz","SourceId":"ebillets_jo2024","SourceType":"Discovered","ContentRoot":"Z:\\EVALUATION\\PROJET\\ebillets_jo2024\\ebillets_jo2024\\obj\\Debug\\net9.0\\compressed\\","BasePath":"_content/ebillets_jo2024","RelativePath":"lib/bootstrap/dist/css/bootstrap.min.css#[.{fingerprint=kao5znno1s}]?.map.gz","AssetKind":"All","AssetMode":"All","AssetRole":"Alternative","AssetMergeBehavior":null,"AssetMergeSource":"","RelatedAsset":"Z:\\EVALUATION\\PROJET\\ebillets_jo2024\\ebillets_jo2024\\wwwroot\\lib\\bootstrap\\dist\\css\\bootstrap.min.css.map","AssetTraitName":"Content-Encoding","AssetTraitValue":"gzip","Fingerprint":"py1k7jl89u","Integrity":"8SkbHnWWeJ8KG1\u002BbQUkOaPN31v/xtm4ZycUWB/SvS20=","CopyToOutputDirectory":"Never","CopyToPublishDirectory":"PreserveNewest","OriginalItemSpec":"Z:\\EVALUATION\\PROJET\\ebillets_jo2024\\ebillets_jo2024\\wwwroot\\lib\\bootstrap\\dist\\css\\bootstrap.min.css.map","FileLength":102069,"LastWriteTime":"2025-10-12T09:03:03.9885812+00:00"},"L7eFClbOW5rabeVwI8ljhe2AQR679AinolCQx\u002BsGba4=":{"Identity":"Z:\\EVALUATION\\PROJET\\ebillets_jo2024\\ebillets_jo2024\\obj\\Debug\\net9.0\\compressed\\krkqeuksyt-u0biprgly9.gz","SourceId":"ebillets_jo2024","SourceType":"Discovered","ContentRoot":"Z:\\EVALUATION\\PROJET\\ebillets_jo2024\\ebillets_jo2024\\obj\\Debug\\net9.0\\compressed\\","BasePath":"_content/ebillets_jo2024","RelativePath":"lib/bootstrap/dist/js/bootstrap.bundle#[.{fingerprint=u0biprgly9}]?.js.gz","AssetKind":"All","AssetMode":"All","AssetRole":"Alternative","AssetMergeBehavior":null,"AssetMergeSource":"","RelatedAsset":"Z:\\EVALUATION\\PROJET\\ebillets_jo2024\\ebillets_jo2024\\wwwroot\\lib\\bootstrap\\dist\\js\\bootstrap.bundle.js","AssetTraitName":"Content-Encoding","AssetTraitValue":"gzip","Fingerprint":"hy9fihjyo6","Integrity":"KcZfC8VlRGpzBSf8kYjbjjvxZ1mENKljqzW5X1VIqCY=","CopyToOutputDirectory":"Never","CopyToPublishDirectory":"PreserveNewest","OriginalItemSpec":"Z:\\EVALUATION\\PROJET\\ebillets_jo2024\\ebillets_jo2024\\wwwroot\\lib\\bootstrap\\dist\\js\\bootstrap.bundle.js","FileLength":48345,"LastWriteTime":"2025-10-12T09:03:03.9950615+00:00"},"NGYnhibmefS/yPQnDZMgkUKeJVttu4eAhdkeHJeaU/8=":{"Identity":"Z:\\EVALUATION\\PROJET\\ebillets_jo2024\\ebillets_jo2024\\obj\\Debug\\net9.0\\compressed\\wrbz1hbym2-pxamm17y9e.gz","SourceId":"ebillets_jo2024","SourceType":"Discovered","ContentRoot":"Z:\\EVALUATION\\PROJET\\ebillets_jo2024\\ebillets_jo2024\\obj\\Debug\\net9.0\\compressed\\","BasePath":"_content/ebillets_jo2024","RelativePath":"lib/bootstrap/dist/js/bootstrap.bundle.js#[.{fingerprint=pxamm17y9e}]?.map.gz","AssetKind":"All","AssetMode":"All","AssetRole":"Alternative","AssetMergeBehavior":null,"AssetMergeSource":"","RelatedAsset":"Z:\\EVALUATION\\PROJET\\ebillets_jo2024\\ebillets_jo2024\\wwwroot\\lib\\bootstrap\\dist\\js\\bootstrap.bundle.js.map","AssetTraitName":"Content-Encoding","AssetTraitValue":"gzip","Fingerprint":"99x6gwa75b","Integrity":"IyKBFJ2NdYfuuICMUQxeCcGk/bTVfEdW5iAvM9nw0oU=","CopyToOutputDirectory":"Never","CopyToPublishDirectory":"PreserveNewest","OriginalItemSpec":"Z:\\EVALUATION\\PROJET\\ebillets_jo2024\\ebillets_jo2024\\wwwroot\\lib\\bootstrap\\dist\\js\\bootstrap.bundle.js.map","FileLength":91460,"LastWriteTime":"2025-10-12T09:03:03.9778884+00:00"},"ck5VqH88wjOuPMIUdb7SCeqOWSMjNPAn2ibXHbthqkk=":{"Identity":"Z:\\EVALUATION\\PROJET\\ebillets_jo2024\\ebillets_jo2024\\obj\\Debug\\net9.0\\compressed\\7avw0jteo8-hjuzisly30.gz","SourceId":"ebillets_jo2024","SourceType":"Discovered","ContentRoot":"Z:\\EVALUATION\\PROJET\\ebillets_jo2024\\ebillets_jo2024\\obj\\Debug\\net9.0\\compressed\\","BasePath":"_content/ebillets_jo2024","RelativePath":"lib/bootstrap/dist/js/bootstrap.bundle.min#[.{fingerprint=hjuzisly30}]?.js.gz","AssetKind":"All","AssetMode":"All","AssetRole":"Alternative","AssetMergeBehavior":null,"AssetMergeSource":"","RelatedAsset":"Z:\\EVALUATION\\PROJET\\ebillets_jo2024\\ebillets_jo2024\\wwwroot\\lib\\bootstrap\\dist\\js\\bootstrap.bundle.min.js","AssetTraitName":"Content-Encoding","AssetTraitValue":"gzip","Fingerprint":"0nrdyyg5oh","Integrity":"1MiwfybWPUf85W8WHsUjrjh6SWZrvKae/f829\u002BFAkhU=","CopyToOutputDirectory":"Never","CopyToPublishDirectory":"PreserveNewest","OriginalItemSpec":"Z:\\EVALUATION\\PROJET\\ebillets_jo2024\\ebillets_jo2024\\wwwroot\\lib\\bootstrap\\dist\\js\\bootstrap.bundle.min.js","FileLength":22298,"LastWriteTime":"2025-10-12T09:03:03.9718883+00:00"},"TjfTgi07Xc\u002BW2UcDcvWVJSetMk6MtP8lOnP4FZnmN6o=":{"Identity":"Z:\\EVALUATION\\PROJET\\ebillets_jo2024\\ebillets_jo2024\\obj\\Debug\\net9.0\\compressed\\v86vykexek-u9xms436mi.gz","SourceId":"ebillets_jo2024","SourceType":"Discovered","ContentRoot":"Z:\\EVALUATION\\PROJET\\ebillets_jo2024\\ebillets_jo2024\\obj\\Debug\\net9.0\\compressed\\","BasePath":"_content/ebillets_jo2024","RelativePath":"lib/bootstrap/dist/js/bootstrap.bundle.min.js#[.{fingerprint=u9xms436mi}]?.map.gz","AssetKind":"All","AssetMode":"All","AssetRole":"Alternative","AssetMergeBehavior":null,"AssetMergeSource":"","RelatedAsset":"Z:\\EVALUATION\\PROJET\\ebillets_jo2024\\ebillets_jo2024\\wwwroot\\lib\\bootstrap\\dist\\js\\bootstrap.bundle.min.js.map","AssetTraitName":"Content-Encoding","AssetTraitValue":"gzip","Fingerprint":"ka41v8yo7c","Integrity":"BHUyrJ6l5FX9FTIykDazdjlP73jzpfplry3r\u002B6zSdoE=","CopyToOutputDirectory":"Never","CopyToPublishDirectory":"PreserveNewest","OriginalItemSpec":"Z:\\EVALUATION\\PROJET\\ebillets_jo2024\\ebillets_jo2024\\wwwroot\\lib\\bootstrap\\dist\\js\\bootstrap.bundle.min.js.map","FileLength":82041,"LastWriteTime":"2025-10-12T09:03:03.9872566+00:00"},"l8qvB0eAjawmyYWSMAZXZy1EPrAKuw7SJG6w8st6nRo=":{"Identity":"Z:\\EVALUATION\\PROJET\\ebillets_jo2024\\ebillets_jo2024\\obj\\Debug\\net9.0\\compressed\\9usez4bdqo-48vr37mrsy.gz","SourceId":"ebillets_jo2024","SourceType":"Discovered","ContentRoot":"Z:\\EVALUATION\\PROJET\\ebillets_jo2024\\ebillets_jo2024\\obj\\Debug\\net9.0\\compressed\\","BasePath":"_content/ebillets_jo2024","RelativePath":"lib/bootstrap/dist/js/bootstrap#[.{fingerprint=48vr37mrsy}]?.js.gz","AssetKind":"All","AssetMode":"All","AssetRole":"Alternative","AssetMergeBehavior":null,"AssetMergeSource":"","RelatedAsset":"Z:\\EVALUATION\\PROJET\\ebillets_jo2024\\ebillets_jo2024\\wwwroot\\lib\\bootstrap\\dist\\js\\bootstrap.js","AssetTraitName":"Content-Encoding","AssetTraitValue":"gzip","Fingerprint":"gd33sbxxto","Integrity":"1Ct5pGkD\u002BFF0LlXrT4xzvGbCR79KcfwrOutx4z65BIc=","CopyToOutputDirectory":"Never","CopyToPublishDirectory":"PreserveNewest","OriginalItemSpec":"Z:\\EVALUATION\\PROJET\\ebillets_jo2024\\ebillets_jo2024\\wwwroot\\lib\\bootstrap\\dist\\js\\bootstrap.js","FileLength":25283,"LastWriteTime":"2025-10-12T09:03:03.9900587+00:00"},"Xso3BC3HnW9OR5E4cDfKQJFvyMKwW7WINsDSzxq0pDU=":{"Identity":"Z:\\EVALUATION\\PROJET\\ebillets_jo2024\\ebillets_jo2024\\obj\\Debug\\net9.0\\compressed\\rkr12rtxse-vaswmcjbo4.gz","SourceId":"ebillets_jo2024","SourceType":"Discovered","ContentRoot":"Z:\\EVALUATION\\PROJET\\ebillets_jo2024\\ebillets_jo2024\\obj\\Debug\\net9.0\\compressed\\","BasePath":"_content/ebillets_jo2024","RelativePath":"lib/bootstrap/dist/js/bootstrap.js#[.{fingerprint=vaswmcjbo4}]?.map.gz","AssetKind":"All","AssetMode":"All","AssetRole":"Alternative","AssetMergeBehavior":null,"AssetMergeSource":"","RelatedAsset":"Z:\\EVALUATION\\PROJET\\ebillets_jo2024\\ebillets_jo2024\\wwwroot\\lib\\bootstrap\\dist\\js\\bootstrap.js.map","AssetTraitName":"Content-Encoding","AssetTraitValue":"gzip","Fingerprint":"t7dzx6h33q","Integrity":"V2nzFYIGfzW4T0n5xREU4Xq27AL4FR\u002BObKGcPUp3R8I=","CopyToOutputDirectory":"Never","CopyToPublishDirectory":"PreserveNewest","OriginalItemSpec":"Z:\\EVALUATION\\PROJET\\ebillets_jo2024\\ebillets_jo2024\\wwwroot\\lib\\bootstrap\\dist\\js\\bootstrap.js.map","FileLength":57786,"LastWriteTime":"2025-10-12T09:03:03.9708874+00:00"},"q\u002BMnEhdfbMl7fpvWk8D4QOnzGD\u002B8HNcm6rTDeRPHNQc=":{"Identity":"Z:\\EVALUATION\\PROJET\\ebillets_jo2024\\ebillets_jo2024\\obj\\Debug\\net9.0\\compressed\\apioz0v0xg-zu238p5lxg.gz","SourceId":"ebillets_jo2024","SourceType":"Discovered","ContentRoot":"Z:\\EVALUATION\\PROJET\\ebillets_jo2024\\ebillets_jo2024\\obj\\Debug\\net9.0\\compressed\\","BasePath":"_content/ebillets_jo2024","RelativePath":"lib/bootstrap/dist/js/bootstrap.min#[.{fingerprint=zu238p5lxg}]?.js.gz","AssetKind":"All","AssetMode":"All","AssetRole":"Alternative","AssetMergeBehavior":null,"AssetMergeSource":"","RelatedAsset":"Z:\\EVALUATION\\PROJET\\ebillets_jo2024\\ebillets_jo2024\\wwwroot\\lib\\bootstrap\\dist\\js\\bootstrap.min.js","AssetTraitName":"Content-Encoding","AssetTraitValue":"gzip","Fingerprint":"b9b8zdnevc","Integrity":"/zGCumvrl91atAvEbBmyY\u002BKKn65ToLyg\u002Bicn9FQP8xU=","CopyToOutputDirectory":"Never","CopyToPublishDirectory":"PreserveNewest","OriginalItemSpec":"Z:\\EVALUATION\\PROJET\\ebillets_jo2024\\ebillets_jo2024\\wwwroot\\lib\\bootstrap\\dist\\js\\bootstrap.min.js","FileLength":15441,"LastWriteTime":"2025-10-12T09:03:03.9738891+00:00"},"OI2ww56DsHf5pRQ5oFnPNw145n7X63QSGI4cmxQEs2M=":{"Identity":"Z:\\EVALUATION\\PROJET\\ebillets_jo2024\\ebillets_jo2024\\obj\\Debug\\net9.0\\compressed\\poygazi1ez-sgi57dik4g.gz","SourceId":"ebillets_jo2024","SourceType":"Discovered","ContentRoot":"Z:\\EVALUATION\\PROJET\\ebillets_jo2024\\ebillets_jo2024\\obj\\Debug\\net9.0\\compressed\\","BasePath":"_content/ebillets_jo2024","RelativePath":"lib/bootstrap/dist/js/bootstrap.min.js#[.{fingerprint=sgi57dik4g}]?.map.gz","AssetKind":"All","AssetMode":"All","AssetRole":"Alternative","AssetMergeBehavior":null,"AssetMergeSource":"","RelatedAsset":"Z:\\EVALUATION\\PROJET\\ebillets_jo2024\\ebillets_jo2024\\wwwroot\\lib\\bootstrap\\dist\\js\\bootstrap.min.js.map","AssetTraitName":"Content-Encoding","AssetTraitValue":"gzip","Fingerprint":"l0a66zixp4","Integrity":"y/W\u002BIS3pBW6YOxougP7451HTyQ/Q1y9J/D94i5Ds7u8=","CopyToOutputDirectory":"Never","CopyToPublishDirectory":"PreserveNewest","OriginalItemSpec":"Z:\\EVALUATION\\PROJET\\ebillets_jo2024\\ebillets_jo2024\\wwwroot\\lib\\bootstrap\\dist\\js\\bootstrap.min.js.map","FileLength":46112,"LastWriteTime":"2025-10-12T09:03:03.9818874+00:00"},"OBHGhoT4a2DyZI9sYHCkTY1hUJCfM9qSPOqIXHLQfDs=":{"Identity":"Z:\\EVALUATION\\PROJET\\ebillets_jo2024\\ebillets_jo2024\\obj\\Debug\\net9.0\\compressed\\wieo78p5ii-dvc2bfcndg.gz","SourceId":"ebillets_jo2024","SourceType":"Discovered","ContentRoot":"Z:\\EVALUATION\\PROJET\\ebillets_jo2024\\ebillets_jo2024\\obj\\Debug\\net9.0\\compressed\\","BasePath":"_content/ebillets_jo2024","RelativePath":"lib/jquery-validation-unobtrusive/jquery.validate.unobtrusive#[.{fingerprint=dvc2bfcndg}]?.js.gz","AssetKind":"All","AssetMode":"All","AssetRole":"Alternative","AssetMergeBehavior":null,"AssetMergeSource":"","RelatedAsset":"Z:\\EVALUATION\\PROJET\\ebillets_jo2024\\ebillets_jo2024\\wwwroot\\lib\\jquery-validation-unobtrusive\\jquery.validate.unobtrusive.js","AssetTraitName":"Content-Encoding","AssetTraitValue":"gzip","Fingerprint":"ia1fp3fsqk","Integrity":"tra5GpUITUrALtnm990ZmXUgYSqsrYHJ2wct2dSXNwo=","CopyToOutputDirectory":"Never","CopyToPublishDirectory":"PreserveNewest","OriginalItemSpec":"Z:\\EVALUATION\\PROJET\\ebillets_jo2024\\ebillets_jo2024\\wwwroot\\lib\\jquery-validation-unobtrusive\\jquery.validate.unobtrusive.js","FileLength":4685,"LastWriteTime":"2025-10-12T09:03:03.9728888+00:00"},"ia4YqHr9zmTVULMutH1QwBlF6NoUOqdyLUUam1KERbE=":{"Identity":"Z:\\EVALUATION\\PROJET\\ebillets_jo2024\\ebillets_jo2024\\obj\\Debug\\net9.0\\compressed\\5rux2rwkzj-gb7ocvbhts.gz","SourceId":"ebillets_jo2024","SourceType":"Discovered","ContentRoot":"Z:\\EVALUATION\\PROJET\\ebillets_jo2024\\ebillets_jo2024\\obj\\Debug\\net9.0\\compressed\\","BasePath":"_content/ebillets_jo2024","RelativePath":"lib/jquery-validation-unobtrusive/jquery.validate.unobtrusive.min#[.{fingerprint=gb7ocvbhts}]?.js.gz","AssetKind":"All","AssetMode":"All","AssetRole":"Alternative","AssetMergeBehavior":null,"AssetMergeSource":"","RelatedAsset":"Z:\\EVALUATION\\PROJET\\ebillets_jo2024\\ebillets_jo2024\\wwwroot\\lib\\jquery-validation-unobtrusive\\jquery.validate.unobtrusive.min.js","AssetTraitName":"Content-Encoding","AssetTraitValue":"gzip","Fingerprint":"y5r6ekb0nn","Integrity":"\u002BuJmiWNDfG3y\u002B8SUapZ3/8iFhrZEO4UoNTds6PJqncM=","CopyToOutputDirectory":"Never","CopyToPublishDirectory":"PreserveNewest","OriginalItemSpec":"Z:\\EVALUATION\\PROJET\\ebillets_jo2024\\ebillets_jo2024\\wwwroot\\lib\\jquery-validation-unobtrusive\\jquery.validate.unobtrusive.min.js","FileLength":2220,"LastWriteTime":"2025-10-12T09:03:03.9585019+00:00"},"BcqYKYAIEh8LALdvigulNdeB23S0vcd7i/zJUP4iGxk=":{"Identity":"Z:\\EVALUATION\\PROJET\\ebillets_jo2024\\ebillets_jo2024\\obj\\Debug\\net9.0\\compressed\\6h7tqax6dh-wqejeusuyq.gz","SourceId":"ebillets_jo2024","SourceType":"Discovered","ContentRoot":"Z:\\EVALUATION\\PROJET\\ebillets_jo2024\\ebillets_jo2024\\obj\\Debug\\net9.0\\compressed\\","BasePath":"_content/ebillets_jo2024","RelativePath":"lib/jquery-validation-unobtrusive/LICENSE#[.{fingerprint=wqejeusuyq}]?.txt.gz","AssetKind":"All","AssetMode":"All","AssetRole":"Alternative","AssetMergeBehavior":null,"AssetMergeSource":"","RelatedAsset":"Z:\\EVALUATION\\PROJET\\ebillets_jo2024\\ebillets_jo2024\\wwwroot\\lib\\jquery-validation-unobtrusive\\LICENSE.txt","AssetTraitName":"Content-Encoding","AssetTraitValue":"gzip","Fingerprint":"qmy2g5n6hh","Integrity":"0k\u002BGY7B37PlcFstK7JIg2ptnyI\u002BBsfB92\u002BjtjLIJOuo=","CopyToOutputDirectory":"Never","CopyToPublishDirectory":"PreserveNewest","OriginalItemSpec":"Z:\\EVALUATION\\PROJET\\ebillets_jo2024\\ebillets_jo2024\\wwwroot\\lib\\jquery-validation-unobtrusive\\LICENSE.txt","FileLength":395,"LastWriteTime":"2025-10-12T09:03:03.9605007+00:00"},"tivk942RSZzx\u002BLndo5xVWKhIW2dQn\u002BJULnWCIkP7qs8=":{"Identity":"Z:\\EVALUATION\\PROJET\\ebillets_jo2024\\ebillets_jo2024\\obj\\Debug\\net9.0\\compressed\\2vfe45khfs-wus95c49fh.gz","SourceId":"ebillets_jo2024","SourceType":"Discovered","ContentRoot":"Z:\\EVALUATION\\PROJET\\ebillets_jo2024\\ebillets_jo2024\\obj\\Debug\\net9.0\\compressed\\","BasePath":"_content/ebillets_jo2024","RelativePath":"lib/jquery-validation/dist/additional-methods#[.{fingerprint=wus95c49fh}]?.js.gz","AssetKind":"All","AssetMode":"All","AssetRole":"Alternative","AssetMergeBehavior":null,"AssetMergeSource":"","RelatedAsset":"Z:\\EVALUATION\\PROJET\\ebillets_jo2024\\ebillets_jo2024\\wwwroot\\lib\\jquery-validation\\dist\\additional-methods.js","AssetTraitName":"Content-Encoding","AssetTraitValue":"gzip","Fingerprint":"qur712kw8c","Integrity":"Pk7e9oX4/\u002BO7Ztv\u002Bd0Yk/GdqClCzkF9l6oJgJLD6RgU=","CopyToOutputDirectory":"Never","CopyToPublishDirectory":"PreserveNewest","OriginalItemSpec":"Z:\\EVALUATION\\PROJET\\ebillets_jo2024\\ebillets_jo2024\\wwwroot\\lib\\jquery-validation\\dist\\additional-methods.js","FileLength":11698,"LastWriteTime":"2025-10-12T09:03:03.9639075+00:00"},"LeKK7lFI\u002BQHJYaNneRcorUxZrJuNcfrA4tvfx8s5u\u002BM=":{"Identity":"Z:\\EVALUATION\\PROJET\\ebillets_jo2024\\ebillets_jo2024\\obj\\Debug\\net9.0\\compressed\\l8zehekddo-sjab29p8z5.gz","SourceId":"ebillets_jo2024","SourceType":"Discovered","ContentRoot":"Z:\\EVALUATION\\PROJET\\ebillets_jo2024\\ebillets_jo2024\\obj\\Debug\\net9.0\\compressed\\","BasePath":"_content/ebillets_jo2024","RelativePath":"lib/jquery-validation/dist/additional-methods.min#[.{fingerprint=sjab29p8z5}]?.js.gz","AssetKind":"All","AssetMode":"All","AssetRole":"Alternative","AssetMergeBehavior":null,"AssetMergeSource":"","RelatedAsset":"Z:\\EVALUATION\\PROJET\\ebillets_jo2024\\ebillets_jo2024\\wwwroot\\lib\\jquery-validation\\dist\\additional-methods.min.js","AssetTraitName":"Content-Encoding","AssetTraitValue":"gzip","Fingerprint":"w2h719sd9u","Integrity":"OLeOSYXppYtjegTqvAF1VW6jF7Rk/TBkhxwj44Fhlbc=","CopyToOutputDirectory":"Never","CopyToPublishDirectory":"PreserveNewest","OriginalItemSpec":"Z:\\EVALUATION\\PROJET\\ebillets_jo2024\\ebillets_jo2024\\wwwroot\\lib\\jquery-validation\\dist\\additional-methods.min.js","FileLength":5460,"LastWriteTime":"2025-10-12T09:03:03.965135+00:00"},"LVgInINb3gTngzQYR9a9O6adKnS8JlNBhKqelysjrkI=":{"Identity":"Z:\\EVALUATION\\PROJET\\ebillets_jo2024\\ebillets_jo2024\\obj\\Debug\\net9.0\\compressed\\n9gygpnlkm-d2pxujwhw3.gz","SourceId":"ebillets_jo2024","SourceType":"Discovered","ContentRoot":"Z:\\EVALUATION\\PROJET\\ebillets_jo2024\\ebillets_jo2024\\obj\\Debug\\net9.0\\compressed\\","BasePath":"_content/ebillets_jo2024","RelativePath":"lib/jquery-validation/dist/jquery.validate#[.{fingerprint=d2pxujwhw3}]?.js.gz","AssetKind":"All","AssetMode":"All","AssetRole":"Alternative","AssetMergeBehavior":null,"AssetMergeSource":"","RelatedAsset":"Z:\\EVALUATION\\PROJET\\ebillets_jo2024\\ebillets_jo2024\\wwwroot\\lib\\jquery-validation\\dist\\jquery.validate.js","AssetTraitName":"Content-Encoding","AssetTraitValue":"gzip","Fingerprint":"scqjpphbl3","Integrity":"LJlWNqc\u002BgAs3U5I\u002BjF4VyB\u002BHKQmiECp60pjSAw/gqhs=","CopyToOutputDirectory":"Never","CopyToPublishDirectory":"PreserveNewest","OriginalItemSpec":"Z:\\EVALUATION\\PROJET\\ebillets_jo2024\\ebillets_jo2024\\wwwroot\\lib\\jquery-validation\\dist\\jquery.validate.js","FileLength":13101,"LastWriteTime":"2025-10-12T09:03:03.9605007+00:00"},"tep8xeq/7WUJ1b5pVdGK8plfgBq5Y8BDT4WS7RniGX8=":{"Identity":"Z:\\EVALUATION\\PROJET\\ebillets_jo2024\\ebillets_jo2024\\obj\\Debug\\net9.0\\compressed\\hbqqayxhy4-4dm14o4hmc.gz","SourceId":"ebillets_jo2024","SourceType":"Discovered","ContentRoot":"Z:\\EVALUATION\\PROJET\\ebillets_jo2024\\ebillets_jo2024\\obj\\Debug\\net9.0\\compressed\\","BasePath":"_content/ebillets_jo2024","RelativePath":"lib/jquery-validation/dist/jquery.validate.min#[.{fingerprint=4dm14o4hmc}]?.js.gz","AssetKind":"All","AssetMode":"All","AssetRole":"Alternative","AssetMergeBehavior":null,"AssetMergeSource":"","RelatedAsset":"Z:\\EVALUATION\\PROJET\\ebillets_jo2024\\ebillets_jo2024\\wwwroot\\lib\\jquery-validation\\dist\\jquery.validate.min.js","AssetTraitName":"Content-Encoding","AssetTraitValue":"gzip","Fingerprint":"41f15l79m5","Integrity":"WEtE86OkwYRC2CNB1ewkbZ\u002BKqi1\u002BCF3HTu2hd7e2V\u002Bk=","CopyToOutputDirectory":"Never","CopyToPublishDirectory":"PreserveNewest","OriginalItemSpec":"Z:\\EVALUATION\\PROJET\\ebillets_jo2024\\ebillets_jo2024\\wwwroot\\lib\\jquery-validation\\dist\\jquery.validate.min.js","FileLength":7505,"LastWriteTime":"2025-10-12T09:03:03.9639075+00:00"},"VVDHv/k8Nl1GTbazhUyhhgSVd1bfn/hXPuKjzxZ/Oiw=":{"Identity":"Z:\\EVALUATION\\PROJET\\ebillets_jo2024\\ebillets_jo2024\\obj\\Debug\\net9.0\\compressed\\2949uu7lms-x0q3zqp4vz.gz","SourceId":"ebillets_jo2024","SourceType":"Discovered","ContentRoot":"Z:\\EVALUATION\\PROJET\\ebillets_jo2024\\ebillets_jo2024\\obj\\Debug\\net9.0\\compressed\\","BasePath":"_content/ebillets_jo2024","RelativePath":"lib/jquery-validation/LICENSE#[.{fingerprint=x0q3zqp4vz}]?.md.gz","AssetKind":"All","AssetMode":"All","AssetRole":"Alternative","AssetMergeBehavior":null,"AssetMergeSource":"","RelatedAsset":"Z:\\EVALUATION\\PROJET\\ebillets_jo2024\\ebillets_jo2024\\wwwroot\\lib\\jquery-validation\\LICENSE.md","AssetTraitName":"Content-Encoding","AssetTraitValue":"gzip","Fingerprint":"tbedkqp182","Integrity":"yZU1lf/p2dEnCHUXYp8G4roAyod23x5MoR4DehwHfrA=","CopyToOutputDirectory":"Never","CopyToPublishDirectory":"PreserveNewest","OriginalItemSpec":"Z:\\EVALUATION\\PROJET\\ebillets_jo2024\\ebillets_jo2024\\wwwroot\\lib\\jquery-validation\\LICENSE.md","FileLength":670,"LastWriteTime":"2025-10-12T09:03:03.9639075+00:00"},"76lr/Mli5TtUXy6Khm5YdkaOv0LbYezBTZGxNUgXjEw=":{"Identity":"Z:\\EVALUATION\\PROJET\\ebillets_jo2024\\ebillets_jo2024\\obj\\Debug\\net9.0\\compressed\\hi5nhtlom5-ukz1g2vv03.gz","SourceId":"ebillets_jo2024","SourceType":"Discovered","ContentRoot":"Z:\\EVALUATION\\PROJET\\ebillets_jo2024\\ebillets_jo2024\\obj\\Debug\\net9.0\\compressed\\","BasePath":"_content/ebillets_jo2024","RelativePath":"lib/jquery/dist/jquery#[.{fingerprint=ukz1g2vv03}]?.js.gz","AssetKind":"All","AssetMode":"All","AssetRole":"Alternative","AssetMergeBehavior":null,"AssetMergeSource":"","RelatedAsset":"Z:\\EVALUATION\\PROJET\\ebillets_jo2024\\ebillets_jo2024\\wwwroot\\lib\\jquery\\dist\\jquery.js","AssetTraitName":"Content-Encoding","AssetTraitValue":"gzip","Fingerprint":"c8qd0da0bu","Integrity":"DLotVoRDYqcFMoTS8SroPXm9UpXes926Aa\u002B3ofzrgI0=","CopyToOutputDirectory":"Never","CopyToPublishDirectory":"PreserveNewest","OriginalItemSpec":"Z:\\EVALUATION\\PROJET\\ebillets_jo2024\\ebillets_jo2024\\wwwroot\\lib\\jquery\\dist\\jquery.js","FileLength":85688,"LastWriteTime":"2025-10-12T09:03:03.9798885+00:00"},"reqdiaijtU9ZJmQCNU//N8a5VHmlv\u002BOZYrGBDJDsVYU=":{"Identity":"Z:\\EVALUATION\\PROJET\\ebillets_jo2024\\ebillets_jo2024\\obj\\Debug\\net9.0\\compressed\\rkho4d0qks-rm8d4uw1xt.gz","SourceId":"ebillets_jo2024","SourceType":"Discovered","ContentRoot":"Z:\\EVALUATION\\PROJET\\ebillets_jo2024\\ebillets_jo2024\\obj\\Debug\\net9.0\\compressed\\","BasePath":"_content/ebillets_jo2024","RelativePath":"lib/jquery/dist/jquery.min#[.{fingerprint=rm8d4uw1xt}]?.js.gz","AssetKind":"All","AssetMode":"All","AssetRole":"Alternative","AssetMergeBehavior":null,"AssetMergeSource":"","RelatedAsset":"Z:\\EVALUATION\\PROJET\\ebillets_jo2024\\ebillets_jo2024\\wwwroot\\lib\\jquery\\dist\\jquery.min.js","AssetTraitName":"Content-Encoding","AssetTraitValue":"gzip","Fingerprint":"3v2ifwm4cl","Integrity":"/y1GgHkCumYARSBECIkQv9Ky561H62\u002Bze1QiqSqM\u002B18=","CopyToOutputDirectory":"Never","CopyToPublishDirectory":"PreserveNewest","OriginalItemSpec":"Z:\\EVALUATION\\PROJET\\ebillets_jo2024\\ebillets_jo2024\\wwwroot\\lib\\jquery\\dist\\jquery.min.js","FileLength":30958,"LastWriteTime":"2025-10-12T09:03:03.9625001+00:00"},"AUWlclhK1xmkpNVECnj/n2v0kZBjSXGMG0jrofpw8yI=":{"Identity":"Z:\\EVALUATION\\PROJET\\ebillets_jo2024\\ebillets_jo2024\\obj\\Debug\\net9.0\\compressed\\xaimdmqmca-dsw5v3fbc5.gz","SourceId":"ebillets_jo2024","SourceType":"Discovered","ContentRoot":"Z:\\EVALUATION\\PROJET\\ebillets_jo2024\\ebillets_jo2024\\obj\\Debug\\net9.0\\compressed\\","BasePath":"_content/ebillets_jo2024","RelativePath":"lib/jquery/dist/jquery.min#[.{fingerprint=dsw5v3fbc5}]?.map.gz","AssetKind":"All","AssetMode":"All","AssetRole":"Alternative","AssetMergeBehavior":null,"AssetMergeSource":"","RelatedAsset":"Z:\\EVALUATION\\PROJET\\ebillets_jo2024\\ebillets_jo2024\\wwwroot\\lib\\jquery\\dist\\jquery.min.map","AssetTraitName":"Content-Encoding","AssetTraitValue":"gzip","Fingerprint":"csd2vju3sx","Integrity":"tAL7CEi5Ztuho7H\u002Bd4iUTSXS1Zk/myZzjuaNCPIB6PY=","CopyToOutputDirectory":"Never","CopyToPublishDirectory":"PreserveNewest","OriginalItemSpec":"Z:\\EVALUATION\\PROJET\\ebillets_jo2024\\ebillets_jo2024\\wwwroot\\lib\\jquery\\dist\\jquery.min.map","FileLength":55216,"LastWriteTime":"2025-10-12T09:03:03.9768883+00:00"},"YD0TK400t81NxySSnydZUinijTSdSIpFMBliDKWMfdk=":{"Identity":"Z:\\EVALUATION\\PROJET\\ebillets_jo2024\\ebillets_jo2024\\obj\\Debug\\net9.0\\compressed\\nf0pbcmirn-afgyafcsqt.gz","SourceId":"ebillets_jo2024","SourceType":"Discovered","ContentRoot":"Z:\\EVALUATION\\PROJET\\ebillets_jo2024\\ebillets_jo2024\\obj\\Debug\\net9.0\\compressed\\","BasePath":"_content/ebillets_jo2024","RelativePath":"lib/jquery/LICENSE#[.{fingerprint=afgyafcsqt}]?.txt.gz","AssetKind":"All","AssetMode":"All","AssetRole":"Alternative","AssetMergeBehavior":null,"AssetMergeSource":"","RelatedAsset":"Z:\\EVALUATION\\PROJET\\ebillets_jo2024\\ebillets_jo2024\\wwwroot\\lib\\jquery\\LICENSE.txt","AssetTraitName":"Content-Encoding","AssetTraitValue":"gzip","Fingerprint":"em4b14lj27","Integrity":"2tL6ssgUvPLUDr8vBWmWHtk\u002B7IqutyuHFEGAG7jexBw=","CopyToOutputDirectory":"Never","CopyToPublishDirectory":"PreserveNewest","OriginalItemSpec":"Z:\\EVALUATION\\PROJET\\ebillets_jo2024\\ebillets_jo2024\\wwwroot\\lib\\jquery\\LICENSE.txt","FileLength":933,"LastWriteTime":"2025-10-12T09:03:03.9768883+00:00"}},"CachedCopyCandidates":{}}